Orbs.py
verify_test.py
orbs_ultra-2.1.0.dist-info/licenses/LICENSE
orbs_ultra-2.1.0.dist-info/METADATA
orbs_ultra-2.1.0.dist-info/WHEEL
orbs_ultra-2.1.0.dist-info/entry_points.txt
orbs_ultra-2.1.0.dist-info/top_level.txt
orbs_ultra-2.1.0.dist-info/RECORD
