Metadata-Version: 2.4
Name: orbs-ultra
Version: 2.1.0
Summary: Système de calculs orbitaux ultra-optimisé avec cache distribué et vectorisation NumPy
Home-page: https://github.com/bakayaro84/Orbs-Ultra
Author: Orbs Development Team
Author-email: tuaea0@gmail.com
Classifier: Development Status :: 5 - Production/Stable
Classifier: Intended Audience :: Science/Research
Classifier: Intended Audience :: Developers
Classifier: Topic :: Scientific/Engineering :: Astronomy
Classifier: Topic :: Scientific/Engineering :: Physics
Classifier: License :: OSI Approved :: MIT License
Classifier: Programming Language :: Python :: 3
Classifier: Programming Language :: Python :: 3.8
Classifier: Programming Language :: Python :: 3.9
Classifier: Programming Language :: Python :: 3.10
Classifier: Programming Language :: Python :: 3.11
Classifier: Operating System :: OS Independent
Requires-Python: >=3.8
License-File: LICENSE
Requires-Dist: numpy>=1.20.0
Requires-Dist: matplotlib>=3.3.0
Provides-Extra: dev
Requires-Dist: pytest>=6.0; extra == "dev"
Requires-Dist: pytest-cov>=2.0; extra == "dev"
Requires-Dist: black>=21.0; extra == "dev"
Requires-Dist: flake8>=3.8; extra == "dev"
Provides-Extra: performance
Requires-Dist: numba>=0.50.0; extra == "performance"
Requires-Dist: scipy>=1.6.0; extra == "performance"
Provides-Extra: full
Requires-Dist: pytest>=6.0; extra == "full"
Requires-Dist: pytest-cov>=2.0; extra == "full"
Requires-Dist: numba>=0.50.0; extra == "full"
Requires-Dist: scipy>=1.6.0; extra == "full"
Dynamic: author
Dynamic: author-email
Dynamic: classifier
Dynamic: description
Dynamic: description-content-type
Dynamic: home-page
Dynamic: license-file
Dynamic: provides-extra
Dynamic: requires-dist
Dynamic: requires-python
Dynamic: summary
